{
    "left_elbow": {
        "joint_keys": [
            "left_shoulder",
            "left_elbow",
            "left_wrist"
        ],
        "joints": {
            "left_shoulder": [
                [
                    -0.5934473430393745,
                    -1.1311789195286992,
                    2.015840437023991
                ],
                [
                    0.9673187357463258,
                    -0.12488334900590753,
                    0.14780693953486776,
                    0.16386494817542502
                ]
            ],
            "left_elbow": [
                [
                    -2.172572717291921,
                    -0.8095921087636558,
                    -0.6279778111296281
                ],
                [
                    -0.30487722050543636,
                    0.5024403767539631,
                    0.5601981392868386,
                    0.5837650151934244
                ]
            ],
            "left_wrist": [
                [
                    -2.037673858527426,
                    -0.5908355807161603,
                    -0.5241081908165292
                ],
                [
                    -0.30485783584238524,
                    0.5024206954770157,
                    0.560211776404977,
                    0.5837789909366979
                ]
            ]
        },
        "degrees": -119.92368045691654
    },
    "right_elbow": {
        "joint_keys": [
            "right_shoulder",
            "right_elbow",
            "right_wrist"
        ],
        "joints": {
            "right_shoulder": [
                [
                    -0.4823411808442572,
                    1.723728886040181,
                    -1.5533095067896283
                ],
                [
                    -0.0035188793247705186,
                    0.03912654871529177,
                    0.09482994694100416,
                    0.9947180564547393
                ]
            ],
            "right_elbow": [
                [
                    1.6665211917263412,
                    -0.040364017428740025,
                    1.6696683562047934
                ],
                [
                    0.7044216108226207,
                    0.7040090126418808,
                    -0.03027826712395737,
                    0.08511598477982224
                ]
            ],
            "right_wrist": [
                [
                    1.643740289781395,
                    0.003181496823354578,
                    1.9424111035897071
                ],
                [
                    0.7044275832736959,
                    0.7040150325367556,
                    -0.030201191256738702,
                    0.08504411756332825
                ]
            ]
        },
        "degrees": 78.05563375995558
    },
    "left_shoulder": {
        "joint_keys": [
            "left_hip",
            "left_shoulder",
            "left_elbow"
        ],
        "joints": {
            "left_hip": [
                [
                    0.41838373345500307,
                    1.283916754404334,
                    1.5028740231245945
                ],
                [
                    0.644463870536758,
                    0.06397124321592088,
                    -0.03387631553768959,
                    0.7612006272066392
                ]
            ],
            "left_shoulder": [
                [
                    -0.5934473430393745,
                    -1.1311789195286992,
                    2.015840437023991
                ],
                [
                    0.9673187357463258,
                    -0.12488334900590753,
                    0.14780693953486776,
                    0.16386494817542502
                ]
            ],
            "left_elbow": [
                [
                    -2.172572717291921,
                    -0.8095921087636558,
                    -0.6279778111296281
                ],
                [
                    -0.30487722050543636,
                    0.5024403767539631,
                    0.5601981392868386,
                    0.5837650151934244
                ]
            ]
        },
        "degrees": -94.72635094451073
    },
    "right_shoulder": {
        "joint_keys": [
            "right_hip",
            "right_shoulder",
            "right_elbow"
        ],
        "joints": {
            "right_hip": [
                [
                    0.4846779039867998,
                    1.294072044984614,
                    1.4490711898581148
                ],
                [
                    0.6284900895838793,
                    0.06284240912680497,
                    -0.10513845377959577,
                    0.7681125857885824
                ]
            ],
            "right_shoulder": [
                [
                    -0.4823411808442572,
                    1.723728886040181,
                    -1.5533095067896283
                ],
                [
                    -0.0035188793247705186,
                    0.03912654871529177,
                    0.09482994694100416,
                    0.9947180564547393
                ]
            ],
            "right_elbow": [
                [
                    1.6665211917263412,
                    -0.040364017428740025,
                    1.6696683562047934
                ],
                [
                    0.7044216108226207,
                    0.7040090126418808,
                    -0.03027826712395737,
                    0.08511598477982224
                ]
            ]
        },
        "degrees": 94.59395189902155
    }
}